csmanip/__init__.py
csmanip/framework.py
csmanip/headless.py
csmanip/trends_climdex.py
csmanip/data_processing/__init__.py
csmanip/data_processing/data_processing.py
csmanip/data_processing/era5_download.py
csmanip/data_processing/noaa_download.py
csmanip/language/language_manager.py
csmanip/machine_learning/__init__.py
csmanip/machine_learning/bagging_trees.py
csmanip/machine_learning/decision_trees.py
csmanip/machine_learning/gaussian_process.py
csmanip/machine_learning/gui_helpers.py
csmanip/machine_learning/machine_learning.py
csmanip/machine_learning/ml.py
csmanip/machine_learning/ml_helpers.py
csmanip/machine_learning/ml_view.py
csmanip/machine_learning/nearest_neighbors.py
csmanip/machine_learning/neural_network.py
csmanip/machine_learning/support_vector.py
csmanip/machine_learning/utils.py
csmanip/machine_learning/view.py
csmanip/meta_learning/__init__.py
csmanip/meta_learning/combine_meta_l.py
csmanip/meta_learning/customized_meta_l.py
csmanip/meta_learning/gen_param.py
csmanip/meta_learning/meta_learning.py
csmanip/meta_learning/meta_view.py
csmanip/meta_learning/test_generat.py
csmanip/meta_learning/tests_generator.py
csmanip/meta_learning/view.py
csmanip/pages/start_page.py
csmanip/pages/tooltip.py
csmanip/pages/utils.py
csmanip/pages/data_imputation/data_imputation_page.py
csmanip/pages/data_imputation/imputation_techniques_page.py
csmanip/pages/data_imputation/triangulation_page.py
csmanip/pages/data_imputation/view_data_page.py
csmanip/pages/data_imputation/machine_learning/gui_helpers.py
csmanip/pages/data_imputation/machine_learning/machine_learning_page.py
csmanip/pages/data_imputation/machine_learning/optuna_popup.py
csmanip/pages/data_imputation/meta_learning/meta_learning_page.py
csmanip/pages/download/download_page.py
csmanip/pages/trends/trends_page.py
csmanip/pages/tutorial/tutorial_page.py
csmanip/styles/colors.py
csmanip/training/__init__.py
csmanip/training/bagging_tree_tr.py
csmanip/training/custom_tree.py
csmanip-0.1.0.dist-info/METADATA
csmanip-0.1.0.dist-info/WHEEL
csmanip-0.1.0.dist-info/top_level.txt
csmanip-0.1.0.dist-info/RECORD
